sortedmusic/__init__.py
sortedmusic-0.0.0.dist-info/DESCRIPTION.rst
sortedmusic-0.0.0.dist-info/METADATA
sortedmusic-0.0.0.dist-info/RECORD
sortedmusic-0.0.0.dist-info/WHEEL
sortedmusic-0.0.0.dist-info/metadata.json
sortedmusic-0.0.0.dist-info/top_level.txt
