Metadata-Version: 2.0
Name: sortedmusic
Version: 0.0.0
Summary: Download, label and organize your music library
Home-page: https://github.com/EtiennePelletier/SortedMusic
Author: Étienne Pelletier
Author-email: etpelletier93@hotmail.com
License: MIT
Keywords: music download organize label sort youtube
Platform: UNKNOWN
Classifier: Development Status :: 1 - Planning
Classifier: License :: OSI Approved :: MIT License
Classifier: Programming Language :: Python :: 3
